pgox/check.cpython-38.so
pgox/check/__init__.py
pgox/check/check.py
pgox_check-0.0.2.dist-info/LICENSE
pgox_check-0.0.2.dist-info/METADATA
pgox_check-0.0.2.dist-info/WHEEL
pgox_check-0.0.2.dist-info/top_level.txt
pgox_check-0.0.2.dist-info/RECORD
