Metadata-Version: 2.1
Name: pgox-check
Version: 0.0.2
Summary: PGOX library for learning purposes
Home-page: https://phoxett.github.io/pgox-check/
Author: Phoxett
Author-email: phoxett@gmail.com
Maintainer: Phoxett
Maintainer-email: phoxett@gmail.com
License: MIT
Platform: UNKNOWN
